odoo10_addon_l10n_it_website_sale_corrispettivi-10.0.1.1.0-py2.7-nspkg.pth
odoo/addons/l10n_it_website_sale_corrispettivi/README.rst
odoo/addons/l10n_it_website_sale_corrispettivi/__init__.py
odoo/addons/l10n_it_website_sale_corrispettivi/__manifest__.py
odoo/addons/l10n_it_website_sale_corrispettivi/controllers/__init__.py
odoo/addons/l10n_it_website_sale_corrispettivi/controllers/main.py
odoo/addons/l10n_it_website_sale_corrispettivi/i18n/it.po
odoo/addons/l10n_it_website_sale_corrispettivi/views/templates.xml
odoo10_addon_l10n_it_website_sale_corrispettivi-10.0.1.1.0.dist-info/DESCRIPTION.rst
odoo10_addon_l10n_it_website_sale_corrispettivi-10.0.1.1.0.dist-info/METADATA
odoo10_addon_l10n_it_website_sale_corrispettivi-10.0.1.1.0.dist-info/RECORD
odoo10_addon_l10n_it_website_sale_corrispettivi-10.0.1.1.0.dist-info/WHEEL
odoo10_addon_l10n_it_website_sale_corrispettivi-10.0.1.1.0.dist-info/metadata.json
odoo10_addon_l10n_it_website_sale_corrispettivi-10.0.1.1.0.dist-info/namespace_packages.txt
odoo10_addon_l10n_it_website_sale_corrispettivi-10.0.1.1.0.dist-info/top_level.txt
